{
  "cache": {
    "extract_hits": 0,
    "extract_misses": 2,
    "fetch_hit": false,
    "root": "C:\\Users\\drew\\rustwx\\proof\\cache"
  },
  "cycle": {
    "date_yyyymmdd": "20260414",
    "hour_utc": 23
  },
  "forecast_hour": 0,
  "grib_url": "https://noaa-rrfs-pds.s3.amazonaws.com/rrfs_a/rrfs.20260414/23/rrfs.t23z.prslev.3km.f000.conus.grib2",
  "model": "rrfs-a",
  "panel_path": "C:\\Users\\drew\\rustwx\\proof\\rustwx_rrfs_a_20260414_23z_f000_midwest_composite_reflectivity_uh.png",
  "recipe": "composite_reflectivity_uh",
  "region": "midwest",
  "source": "aws",
  "timing_ms": {
    "extract": 161,
    "fetch": 370,
    "parse": 0,
    "project": 64,
    "render": 1069,
    "total": 1666
  }
}